drexelfetch/cli.py
drexelfetch/courses.csv
drexelfetch/fetch.py
drexelfetch/helpers.py
drexelfetch-0.2.0.dist-info/LICENSE
drexelfetch-0.2.0.dist-info/METADATA
drexelfetch-0.2.0.dist-info/WHEEL
drexelfetch-0.2.0.dist-info/entry_points.txt
drexelfetch-0.2.0.dist-info/RECORD
