Metadata-Version: 2.1
Name: drexelfetch
Version: 0.2.0
Summary: A fetch tool for drexel courses
License: MIT
Author: dotzenith
Author-email: contact@danshu.co
Requires-Python: >=3.11,<4.0
Classifier: License :: OSI Approved :: MIT License
Classifier: Programming Language :: Python :: 3
Classifier: Programming Language :: Python :: 3.11
Requires-Dist: kolorz (>=0.2.5,<0.3.0)
Requires-Dist: polars (>=0.16.8,<0.17.0)
Requires-Dist: typer (>=0.7.0,<0.8.0)
